Workbook

Sheet Model
A1: Example 4.6 Finding an optimal investment strategy at Barney-Jones -- Investments with irregular timing of returns, page 177
A3: Inputs
A4: Initial amount to invest | B4: 100000
A5: Maximum per investment | B5: 75000
A6: Interest rate on cash | B6: 0.03
A8: Cash outlays on investments (all incurred at beginning of year)
B9: Investment
A10: Year | B10: A | C10: B | D10: C | E10: D | F10: E
A11: 1 | B11: 1 | C11: 0 | D11: 1 | E11: 0 | F11: 0
A12: 2 | B12: 0 | C12: 1 | D12: 0 | E12: 0 | F12: 0
A13: 3 | B13: 0 | C13: 0 | D13: 0 | E13: 0 | F13: 1
A14: 4 | B14: 0 | C14: 0 | D14: 0 | E14: 1 | F14: 0
A16: Cash returns from investments (all incurred at beginning of year)
B17: Investment
A18: Year | B18: A | C18: B | D18: C | E18: D | F18: E
A19: 1 | B19: 0 | C19: 0 | D19: 0 | E19: 0 | F19: 0
A20: 2 | B20: 0.5 | C20: 0 | D20: 1.2 | E20: 0 | F20: 0
A21: 3 | B21: 1 | C21: 0.5 | D21: 0 | E21: 0 | F21: 0
A22: 4 | B22: 0 | C22: 1 | D22: 0 | E22: 0 | F22: 1.5
A23: 5 | B23: 0 | C23: 0 | D23: 0 | E23: 1.9 | F23: 0
A25: Investment decisions
A26: Dollars invested
A28: Maximum per investment
A30: Constraints on cash balance
A31: Year | B31: Beginning cash | C31: Returns from investments | D31: Cash invested | E31: Cash after investing
A32: 1
A33: 2
A34: 3
A35: 4
A36: 5
A38: Final cash

Sheet Investing Model
A1: Barney-Jones Investment Model
A3: INPUTS
A4: Initial amount to invest | B4: 100000
A5: Maximum per investment | B5: 75000
A6: Interest rate on cash (money market) | B6: 0.03
A8: CASH OUTLAYS PER DOLLAR INVESTED (at beginning of year)
A9: Year | B9: Inv A | C9: Inv B | D9: Inv C | E9: Inv D | F9: Inv E
A10: 1 | B10: 1 | C10: 0 | D10: 1 | E10: 0 | F10: 0
A11: 2 | B11: 0 | C11: 1 | D11: 0 | E11: 0 | F11: 0
A12: 3 | B12: 0 | C12: 0 | D12: 0 | E12: 0 | F12: 1
A13: 4 | B13: 0 | C13: 0 | D13: 0 | E13: 1 | F13: 0
A15: CASH RETURNS PER DOLLAR INVESTED (at beginning of year)
A16: Year | B16: Inv A | C16: Inv B | D16: Inv C | E16: Inv D | F16: Inv E
A17: 1 | B17: 0 | C17: 0 | D17: 0 | E17: 0 | F17: 0
A18: 2 | B18: 0.5 | C18: 0 | D18: 1.2 | E18: 0 | F18: 0
A19: 3 | B19: 1 | C19: 0.5 | D19: 0 | E19: 0 | F19: 0
A20: 4 | B20: 0 | C20: 1 | D20: 0 | E20: 0 | F20: 1.5
A21: 5 | B21: 0 | C21: 0 | D21: 0 | E21: 1.9 | F21: 0
A23: INVESTMENT DECISIONS (Decision Variables)
A24: Dollars Invested | B24: Inv A | C24: Inv B | D24: Inv C | E24: Inv D | F24: Inv E
A25: Amount ($) | B25: 64285.714 | C25: 75000 | D25: 35714.286 | E25: 75000 | F25: 75000
B26: <= | C26: <= | D26: <= | E26: <= | F26: <=
A27: Maximum per investment | B27: =$B$5 -> 75000 | C27: =$B$5 -> 75000 | D27: =$B$5 -> 75000 | E27: =$B$5 -> 75000 | F27: =$B$5 -> 75000
A29: CASH FLOW SCHEDULE
A30: Year | B30: Beginning Cash | C30: Returns Received | D30: Cash Invested | E30: Cash After Investing | G30: Min
A31: 1 | B31: =B4 -> 100000 | C31: =SUMPRODUCT(B17:F17,$B$25:$F$25) -> 0 | D31: =SUMPRODUCT(B10:F10,$B$25:$F$25) -> 100000 | E31: =B31+C31-D31 -> 0 | F31: >= | G31: 0
A32: 2 | B32: =E31*(1+$B$6) -> 0 | C32: =SUMPRODUCT(B18:F18,$B$25:$F$25) -> 75000 | D32: =SUMPRODUCT(B11:F11,$B$25:$F$25) -> 75000 | E32: =B32+C32-D32 -> -1.2470991e-08 | F32: >= | G32: 0
A33: 3 | B33: =E32*(1+$B$6) -> -1.2845121e-08 | C33: =SUMPRODUCT(B19:F19,$B$25:$F$25) -> 101785.71 | D33: =SUMPRODUCT(B12:F12,$B$25:$F$25) -> 75000 | E33: =B33+C33-D33 -> 26785.714 | F33: >= | G33: 0
A34: 4 | B34: =E33*(1+$B$6) -> 27589.286 | C34: =SUMPRODUCT(B20:F20,$B$25:$F$25) -> 187500 | D34: =SUMPRODUCT(B13:F13,$B$25:$F$25) -> 75000 | E34: =B34+C34-D34 -> 140089.29 | F34: >= | G34: 0
A35: 5 | B35: =E34*(1+$B$6) -> 144291.96 | C35: =SUMPRODUCT(B21:F21,$B$25:$F$25) -> 142500
A37: OBJECTIVE
A38: Maximize Final Cash (Year 5) | B38: =B35+C35 -> 286791.96
A40: SOLVER CONFIGURATION
A41: Set Objective | B41: B38 (Maximize Final Cash)
A42: Changing Variable Cells | B42: B25:F25 (Dollars invested in each investment)
A43: Constraint 1 | B43: B25:F25 <= B27:F27 (max per investment)
A44: Constraint 2 | B44: E31:E34 >= 0 (cash after investing must be non-negative)
A45: Method | B45: Simplex LP | Non-negative

Sheet Min Investment
A1: — Modified Barney-Jones: Minimum Investment
A3: MODIFICATION
A4: Replace 'Maximum per investment' with 'Minimum investment' — each investment must receive at least the minimum amount shown below.
A5: use $50,000 as the minimum for each investment.
A7: INPUTS
A8: Initial amount to invest | B8: ='Investing Model'!B4 -> 100000
A9: Interest rate on cash (money market) | B9: ='Investing Model'!B6 -> 0.03
A11: MINIMUM INVESTMENT PER INVESTMENT (inputs — can vary by investment)
B12: Inv A | C12: Inv B | D12: Inv C | E12: Inv D | F12: Inv E
A13: Minimum Investment | B13: 50000 | C13: 50000 | D13: 50000 | E13: 50000 | F13: 50000
A15: INVESTMENT DECISIONS (Decision Variables)
A16: Dollars Invested | B16: Inv A | C16: Inv B | D16: Inv C | E16: Inv D | F16: Inv E
A17: Amount ($) | B17: 50000 | C17: 85000 | D17: 50000 | E17: 223750 | F17: 92500
B18: >= | C18: >= | D18: >= | E18: >= | F18: >=
A19: Minimum Investment | B19: =B13 -> 50000 | C19: =C13 -> 50000 | D19: =D13 -> 50000 | E19: =E13 -> 50000 | F19: =F13 -> 50000
A21: CASH FLOW SCHEDULE
A22: Year | B22: Beginning Cash | C22: Returns Received | D22: Cash Invested | E22: Cash After Investing | G22: Min
A23: 1 | B23: ='Investing Model'!B4 -> 100000 | C23: =SUMPRODUCT('Investing Model'!B17:F17,$B$17:$F$17) -> 0 | D23: =SUMPRODUCT('Investing Model'!B10:F10,$B$17:$F$17) -> 100000 | E23: =B23+C23-D23 -> 0 | F23: >= | G23: 0
A24: 2 | B24: =E23*(1+$B$9) -> 0 | C24: =SUMPRODUCT('Investing Model'!B18:F18,$B$17:$F$17) -> 85000 | D24: =SUMPRODUCT('Investing Model'!B11:F11,$B$17:$F$17) -> 85000 | E24: =B24+C24-D24 -> 2.910383e-08 | F24: >= | G24: 0
A25: 3 | B25: =E24*(1+$B$9) -> 2.9976945e-08 | C25: =SUMPRODUCT('Investing Model'!B19:F19,$B$17:$F$17) -> 92500 | D25: =SUMPRODUCT('Investing Model'!B12:F12,$B$17:$F$17) -> 92500 | E25: =B25+C25-D25 -> 1.1292286e-07 | F25: >= | G25: 0
A26: 4 | B26: =E25*(1+$B$9) -> 1.1631055e-07 | C26: =SUMPRODUCT('Investing Model'!B20:F20,$B$17:$F$17) -> 223750 | D26: =SUMPRODUCT('Investing Model'!B13:F13,$B$17:$F$17) -> 223750 | E26: =B26+C26-D26 -> -2.1705637e-07 | F26: >= | G26: 0
A27: 5 | B27: =E26*(1+$B$9) -> -2.2356806e-07 | C27: =SUMPRODUCT('Investing Model'!B21:F21,$B$17:$F$17) -> 425125
A29: OBJECTIVE
A30: Maximize Final Cash (Year 5) | B30: =B27+C27 -> 425125
A32: SOLVER CONFIGURATION
A33: Set Objective | B33: B30 (Maximize Final Cash)
A34: Changing Variable Cells | B34: B17:F17 (Dollars invested)
A35: Constraint 1 — KEY CHANGE | B35: B17:F17 >= B19:F19 (dollars invested ≥ minimum investment)
A36: Constraint 2 | B36: E23:E26 >= 0 (cash after investing must be non-negative)
A37: Method | B37: Simplex LP | Non-negative
